AUTHORS
COPYING
MANIFEST.in
README
build.sh
ez_setup.py
gen-doc-api.sh
setup.cfg
setup.py
emotion/__init__.py
emotion/emotion.c_emotion.pyx
examples/emotion_test.py
include/emotion/__init__.py
include/emotion/c_emotion.pxd
python_emotion.egg-info/PKG-INFO
python_emotion.egg-info/SOURCES.txt
python_emotion.egg-info/dependency_links.txt
python_emotion.egg-info/not-zip-safe
python_emotion.egg-info/requires.txt
python_emotion.egg-info/top_level.txt